{"chunk_definitions":[{"row":13,"row_count":1,"visible":true,"expansion_state":0,"options":{"engine":"r","label":"unnamed-chunk-10","dev":"png"},"document_id":"B1646C2B","chunk_id":"c3eyflo8pqv2a","chunk_label":"unnamed-chunk-1"},{"row":21,"row_count":1,"visible":true,"expansion_state":0,"options":{"engine":"r","label":"unnamed-chunk-11","dev":"png"},"document_id":"B1646C2B","chunk_id":"cveio6rbqnql2","chunk_label":"unnamed-chunk-2"},{"row":27,"row_count":1,"visible":true,"expansion_state":0,"options":{"engine":"r","label":"unnamed-chunk-12","dev":"png"},"document_id":"B1646C2B","chunk_id":"csm0hfa9hg06z","chunk_label":"unnamed-chunk-3"},{"row":33,"row_count":1,"visible":true,"expansion_state":0,"options":{"engine":"r","label":"unnamed-chunk-13","dev":"png"},"document_id":"B1646C2B","chunk_id":"c7vhqleav2mmg","chunk_label":"unnamed-chunk-4"}],"doc_write_time":1771433393}